HISTORY.rst
LICENSE.rst
MANIFEST.in
README.rst
setup.py
collective/.DS_Store
collective/__init__.py
collective/__init__.pyc
collective.contextimageexamples.egg-info/PKG-INFO
collective.contextimageexamples.egg-info/SOURCES.txt
collective.contextimageexamples.egg-info/dependency_links.txt
collective.contextimageexamples.egg-info/entry_points.txt
collective.contextimageexamples.egg-info/namespace_packages.txt
collective.contextimageexamples.egg-info/not-zip-safe
collective.contextimageexamples.egg-info/requires.txt
collective.contextimageexamples.egg-info/top_level.txt
collective/contextimageexamples/.DS_Store
collective/contextimageexamples/__init__.py
collective/contextimageexamples/__init__.pyc
collective/contextimageexamples/configure.zcml
collective/contextimageexamples/profiles/.DS_Store
collective/contextimageexamples/profiles/default/.DS_Store
collective/contextimageexamples/profiles/default/metadata.xml
collective/contextimageexamples/profiles/default/types.xml
collective/contextimageexamples/profiles/default/types/Filetype.xml
collective/contextimageexamples/profiles/footer/.DS_Store
collective/contextimageexamples/profiles/footer/metadata.xml
collective/contextimageexamples/profiles/header/.DS_Store
collective/contextimageexamples/profiles/header/metadata.xml
collective/contextimageexamples/profiles/page/.DS_Store
collective/contextimageexamples/profiles/page/metadata.xml
collective/contextimageexamples/profiles/viewlet/.DS_Store
collective/contextimageexamples/profiles/viewlet/metadata.xml