Metadata-Version: 1.0
Name: collective.contextimageexamples
Version: 0.1
Summary: Some examples for context.contextimage
Home-page: http://pypi.python.org/pypi/collective.contextimageexamples
Author: Espen Moe-Nilssen
Author-email: espen@medialog.no
License: GPL
Keywords: web zope plone theme context.contextimage
Platform: UNKNOWN
Classifier: License :: OSI Approved :: GNU General Public License (GPL)
Classifier: Operating System :: OS Independent
Classifier: Programming Language :: Python
Classifier: Topic :: Software Development
Classifier: Framework :: Plone
Classifier: Framework :: Plone :: 4.1
Classifier: Framework :: Plone :: 4.2
